{
  "appUsers": [
    {
      "id": "1",
      "email": "test@example.com",
      "password": "password123.",
      "name": "Adedeji",
      "firstName": "Simisola",
      "lastName": "Adedeji",
      "profilePhoto": "/images/userAvatar.png",
      "organizations": [
        "Lendsqr", "Irorun"
      ]
    }
  ],
  "notifications": [
    {
      "notification_id": 1,
      "notification_timestamp": "2024-02-05 15:49:00",
      "notification_message": "Integer tincidunt ante vel ipsum. Praesent blandit lacinia erat. Vestibulum sed magna at nunc commodo placerat.",
      "notification_image": "http://dummyimage.com/215x100.png/cc0000/ffffff"
    },
    {
      "notification_id": 2,
      "notification_timestamp": "2024-02-01 01:41:09",
      "notification_message": "Nulla tellus.",
      "notification_image": "http://dummyimage.com/207x100.png/ff4444/ffffff"
    },
    {
      "notification_id": 3,
      "notification_timestamp": "2024-01-15 05:21:32",
      "notification_message": "Nam congue, risus semper porta volutpat, quam pede lobortis ligula, sit amet eleifend pede libero quis orci. Nullam molestie nibh in lectus.",
      "notification_image": "http://dummyimage.com/221x100.png/cc0000/ffffff"
    },
    {
      "notification_id": 4,
      "notification_timestamp": "2024-02-06 06:13:31",
      "notification_message": "Suspendisse potenti. Nullam porttitor lacus at turpis. Donec posuere metus vitae ipsum.",
      "notification_image": "http://dummyimage.com/146x100.png/ff4444/ffffff"
    },
    {
      "notification_id": 5,
      "notification_timestamp": "2024-01-16 08:36:17",
      "notification_message": "Vivamus vestibulum sagittis sapien. Cum sociis natoque penatibus et magnis dis parturient montes, nascetur ridiculus mus. Etiam vel augue.",
      "notification_image": "http://dummyimage.com/154x100.png/ff4444/ffffff"
    },
    {
      "notification_id": 6,
      "notification_timestamp": "2024-01-24 11:05:17",
      "notification_message": "Duis bibendum. Morbi non quam nec dui luctus rutrum.",
      "notification_image": "http://dummyimage.com/155x100.png/ff4444/ffffff"
    },
    {
      "notification_id": 7,
      "notification_timestamp": "2024-01-06 03:02:59",
      "notification_message": "Quisque porta volutpat erat. Quisque erat eros, viverra eget, congue eget, semper rutrum, nulla. Nunc purus.",
      "notification_image": "http://dummyimage.com/159x100.png/dddddd/000000"
    },
    {
      "notification_id": 8,
      "notification_timestamp": "2024-02-13 00:04:18",
      "notification_message": "Morbi non quam nec dui luctus rutrum. Nulla tellus.",
      "notification_image": "http://dummyimage.com/177x100.png/5fa2dd/ffffff"
    },
    {
      "notification_id": 9,
      "notification_timestamp": "2024-02-14 19:09:35",
      "notification_message": "Mauris ullamcorper purus sit amet nulla. Quisque arcu libero, rutrum ac, lobortis vel, dapibus at, diam.",
      "notification_image": "http://dummyimage.com/236x100.png/dddddd/000000"
    },
    {
      "notification_id": 10,
      "notification_timestamp": "2024-02-09 10:38:07",
      "notification_message": "Sed sagittis. Nam congue, risus semper porta volutpat, quam pede lobortis ligula, sit amet eleifend pede libero quis orci.",
      "notification_image": "http://dummyimage.com/218x100.png/dddddd/000000"
    }
  ],
  "userDashboardMetrics": {
    "allUsers": 2453,
    "activeUsers": 2453,
    "usersWithLoans": 12453,
    "usersWithSavings": 102453
  },
  "users": [
    {
      "id": "01J12AR7W62BBJ2DVWK7PKR6SB",
      "organization": "Lendsqr",
      "userName": "Adedeji",
      "email": "adedeji@lendsqr.com",
      "phoneNumber": "08078903721",
      "dateJoined": "2020-05-15 10:00:00",
      "status": "inactive"
    }, {
      "id": "01J12AR7W8B7YJ3XS6D9CREWEE",
      "organization": "Irorun",
      "userName": "Debby Ogana",
      "email": "debby2@irorun.com",
      "phoneNumber": "08160780928",
      "dateJoined": "2020-04-20 10:00:00",
      "status": "pending"
    }, {
      "id": "01J12AR7W9Q9CDPTYC0Q7KJV3D",
      "organization": "Lendsqr",
      "userName": "Grace Effiom",
      "email": "afudger2@google.de",
      "phoneNumber": "5065155438",
      "dateJoined": "2022-11-06 00:35:54",
      "status": "active"
    }, {
      "id": "01J12AR7WAB8AM1BQ7WHTFB1HY",
      "organization": "Lendsqr",
      "userName": "Tosin Dokunmu",
      "email": "dwoodrooffe3@geocities.jp",
      "phoneNumber": "8244108733",
      "dateJoined": "2021-08-24 22:51:15",
      "status": "active"
    }, {
      "id": "01J12AR7WBRM3C9K17AR40NFT2",
      "organization": "Lendsqr",
      "userName": "Grace Effiom",
      "email": "htinkham4@1und1.de",
      "phoneNumber": "8611900705",
      "dateJoined": "2020-07-01 03:10:24",
      "status": "pending"
    }, {
      "id": "01J12AR7WCF4QN62VK7AQ912BR",
      "organization": "Lendsqr",
      "userName": "Hamnet Huxham",
      "email": "hhuxham5@quantcast.com",
      "phoneNumber": "5482807541",
      "dateJoined": "2021-07-06 05:01:29",
      "status": "blacklisted"
    }, {
      "id": "01J12AR7WDHXASAMMZWNTFV4XX",
      "organization": "Lendsqr",
      "userName": "Gretchen Laffoley-Lane",
      "email": "glaffoleylane6@shop-pro.jp",
      "phoneNumber": "4621806190",
      "dateJoined": "2022-03-29 19:59:36",
      "status": "blacklisted"
    }, {
      "id": "01J12AR7WE5PJGYWP1EGVQSHTH",
      "organization": "Lendsqr",
      "userName": "Madelin Domeny",
      "email": "mdomeny7@amazon.co.uk",
      "phoneNumber": "7733800705",
      "dateJoined": "2021-09-19 08:41:48",
      "status": "active"
    }, {
      "id": "01J12AR7WFBTWPHCN1H154P8Q5",
      "organization": "Lendsqr",
      "userName": "Ginnie Bottrell",
      "email": "gbottrell8@archive.org",
      "phoneNumber": "2026056644",
      "dateJoined": "2022-08-21 17:13:24",
      "status": "pending"
    }, {
      "id": "01J12AR7WGJYAMQ8FA8GZZVED2",
      "organization": "Lendsqr",
      "userName": "Byrle Croston",
      "email": "bcroston9@ebay.com",
      "phoneNumber": "2445925290",
      "dateJoined": "2020-08-26 20:24:29",
      "status": "pending"
    }, {
      "id": "01J12AR7WHY92089466K2CHZS3",
      "organization": "Lendsqr",
      "userName": "Mahala Divers",
      "email": "mdiversa@gmpg.org",
      "phoneNumber": "6056677062",
      "dateJoined": "2023-07-29 21:39:55",
      "status": "active"
    }, {
      "id": "01J12AR7WJ7Q8RCPN4D29C8M94",
      "organization": "O'Conner LLC",
      "userName": "Danielle Rooney",
      "email": "drooneyb@google.ca",
      "phoneNumber": "2104376647",
      "dateJoined": "2022-07-28 10:51:19",
      "status": "active"
    }, {
      "id": "01J12AR7WKXGCVDFM6SJKPN0E7",
      "organization": "MacGyver-Emmerich",
      "userName": "Dyanne Prater",
      "email": "dpraterc@cyberchimps.com",
      "phoneNumber": "9902292501",
      "dateJoined": "2022-12-25 18:28:37",
      "status": "pending"
    }, {
      "id": "01J12AR7WM5D4PKACJJ2Q9Y3BV",
      "organization": "Sawayn, Lowe and Ebert",
      "userName": "Wernher Blabber",
      "email": "wblabberd@businessinsider.com",
      "phoneNumber": "2007607710",
      "dateJoined": "2023-02-25 04:30:16",
      "status": "blacklisted"
    }, {
      "id": "01J12AR7WNCNR55MYQD3XPX6PR",
      "organization": "Considine-Baumbach",
      "userName": "Hayward Tappington",
      "email": "htappingtone@arizona.edu",
      "phoneNumber": "6405891191",
      "dateJoined": "2023-09-01 08:17:39",
      "status": "inactive"
    }, {
      "id": "01J12AR7WPQ3QZHMZF84K72W1K",
      "organization": "Flatley, Stiedemann and Flatley",
      "userName": "Halette Girardet",
      "email": "hgirardetf@de.vu",
      "phoneNumber": "3534553386",
      "dateJoined": "2022-03-07 15:26:01",
      "status": "active"
    }, {
      "id": "01J12AR7WQ89XWHM7D713M357Q",
      "organization": "Batz, Lueilwitz and Koss",
      "userName": "Gail McKeller",
      "email": "gmckellerg@ow.ly",
      "phoneNumber": "3762695946",
      "dateJoined": "2021-08-24 21:44:48",
      "status": "blacklisted"
    }, {
      "id": "01J12AR7WRWXMV0VR7TJAG2QME",
      "organization": "Lemke, Cole and Hilpert",
      "userName": "Jamil Jonin",
      "email": "jjoninh@shop-pro.jp",
      "phoneNumber": "3041758682",
      "dateJoined": "2020-11-06 04:41:10",
      "status": "inactive"
    }, {
      "id": "01J12AR7WS0V59MMC90551EXPR",
      "organization": "Marks and Sons",
      "userName": "Deedee Flavelle",
      "email": "dflavellei@goodreads.com",
      "phoneNumber": "2776648199",
      "dateJoined": "2023-07-03 17:08:54",
      "status": "inactive"
    }, {
      "id": "01J12AR7WTT9YZM5V1VZ6C4M5Q",
      "organization": "Grimes Inc",
      "userName": "Fredek Teaser",
      "email": "fteaserj@mysql.com",
      "phoneNumber": "4107453401",
      "dateJoined": "2020-08-09 07:43:17",
      "status": "active"
    }, {
      "id": "01J12AR7WV028ZY14Q4YPZNCH2",
      "organization": "Schuppe, Hand and Conn",
      "userName": "Lionello Fechnie",
      "email": "lfechniek@live.com",
      "phoneNumber": "9564524000",
      "dateJoined": "2021-05-20 04:17:15",
      "status": "inactive"
    }, {
      "id": "01J12AR7WXG2Z1W57MHFFJDN50",
      "organization": "Wintheiser, Beer and Grady",
      "userName": "Nady Giamelli",
      "email": "ngiamellil@webeden.co.uk",
      "phoneNumber": "7943287162",
      "dateJoined": "2020-08-05 02:08:06",
      "status": "active"
    }, {
      "id": "01J12AR7WYHHSPZH279HW4VA5Y",
      "organization": "Lehner-Bailey",
      "userName": "Marquita Lund",
      "email": "mlundm@elegantthemes.com",
      "phoneNumber": "4667082279",
      "dateJoined": "2022-10-02 11:20:45",
      "status": "inactive"
    }, {
      "id": "01J12AR7WZ53HFDE0KC88AEWDP",
      "organization": "Fay, Weimann and Hudson",
      "userName": "Yuma Kidwell",
      "email": "ykidwelln@tinyurl.com",
      "phoneNumber": "1599281167",
      "dateJoined": "2020-06-23 19:20:41",
      "status": "blacklisted"
    }, {
      "id": "01J12AR7X07B6JXV2CK9V2SRF4",
      "organization": "Morissette, Roob and Lueilwitz",
      "userName": "Gilberte Faraday",
      "email": "gfaradayo@g.co",
      "phoneNumber": "2834869082",
      "dateJoined": "2020-12-24 14:40:14",
      "status": "pending"
    }, {
      "id": "01J12AR7X10DN7B5S7ZBT96NEK",
      "organization": "Grady and Sons",
      "userName": "Raine Scogin",
      "email": "rscoginp@hibu.com",
      "phoneNumber": "1194858158",
      "dateJoined": "2022-08-09 18:41:31",
      "status": "inactive"
    }, {
      "id": "01J12AR7X21B6BQV099063CJH1",
      "organization": "Mayer, Romaguera and Bauch",
      "userName": "Eugenia Dewar",
      "email": "edewarq@marketwatch.com",
      "phoneNumber": "7395901414",
      "dateJoined": "2022-01-19 22:37:10",
      "status": "inactive"
    }, {
      "id": "01J12AR7X36ZJTRJAAGJETNVMR",
      "organization": "Ondricka-Morar",
      "userName": "Dame Craigg",
      "email": "dcraiggr@yelp.com",
      "phoneNumber": "6803418619",
      "dateJoined": "2022-12-25 04:32:23",
      "status": "inactive"
    }, {
      "id": "01J12AR7X432C33J0W7MGM6A66",
      "organization": "Moore and Sons",
      "userName": "Kath Sandey",
      "email": "ksandeys@tuttocitta.it",
      "phoneNumber": "8263883328",
      "dateJoined": "2023-08-18 15:33:30",
      "status": "active"
    }, {
      "id": "01J12AR7X569FRETS2MAHZKT88",
      "organization": "Casper and Sons",
      "userName": "Cyrill Pelos",
      "email": "cpelost@indiegogo.com",
      "phoneNumber": "3542266019",
      "dateJoined": "2022-08-06 09:22:01",
      "status": "active"
    }, {
      "id": "01J12AR7X66REZ6WAPCAJ50CAF",
      "organization": "Stehr-Hammes",
      "userName": "Vivi Squeers",
      "email": "vsqueersu@studiopress.com",
      "phoneNumber": "7493210341",
      "dateJoined": "2022-05-22 01:53:26",
      "status": "pending"
    }, {
      "id": "01J12AR7X70AF8JVFKME7D9WQE",
      "organization": "Bogisich, Pacocha and D'Amore",
      "userName": "Zacherie Shippey",
      "email": "zshippeyv@indiatimes.com",
      "phoneNumber": "2116038456",
      "dateJoined": "2022-12-17 11:09:31",
      "status": "active"
    }, {
      "id": "01J12AR7X8MFSEP2DERS78VTRS",
      "organization": "Prohaska, Dickinson and Fadel",
      "userName": "Marjie Sigg",
      "email": "msiggw@nbcnews.com",
      "phoneNumber": "6139672058",
      "dateJoined": "2021-11-13 02:42:16",
      "status": "pending"
    }, {
      "id": "01J12AR7X9T899QAAVS3TR60WM",
      "organization": "Stroman LLC",
      "userName": "Esteban Duncombe",
      "email": "eduncombex@yale.edu",
      "phoneNumber": "3028797522",
      "dateJoined": "2022-10-23 19:53:59",
      "status": "blacklisted"
    }, {
      "id": "01J12AR7XAA5QKR9YSWGASYMEE",
      "organization": "Bartell, Schinner and Koss",
      "userName": "Beulah Corston",
      "email": "bcorstony@pagesperso-orange.fr",
      "phoneNumber": "2323160078",
      "dateJoined": "2024-05-27 08:41:02",
      "status": "pending"
    }, {
      "id": "01J12AR7XBECVE7Q0FF23G1HFG",
      "organization": "Donnelly-Simonis",
      "userName": "Hailey Cicchillo",
      "email": "hcicchilloz@ibm.com",
      "phoneNumber": "7478817008",
      "dateJoined": "2020-12-21 08:03:41",
      "status": "blacklisted"
    }, {
      "id": "01J12AR7XCEFTYA8P25NZ4P3PM",
      "organization": "Cormier, Bode and Mann",
      "userName": "Anissa Bollard",
      "email": "abollard10@nba.com",
      "phoneNumber": "4226231892",
      "dateJoined": "2022-04-02 03:31:41",
      "status": "blacklisted"
    }, {
      "id": "01J12AR7XDNNAHJBZ9H3659NTZ",
      "organization": "Mayer-Leffler",
      "userName": "Fay Seligson",
      "email": "fseligson11@google.cn",
      "phoneNumber": "1175850365",
      "dateJoined": "2020-10-13 13:06:06",
      "status": "active"
    }, {
      "id": "01J12AR7XERA751KNNEHZAY8EN",
      "organization": "Hegmann-Gorczany",
      "userName": "Wilmer Seagrove",
      "email": "wseagrove12@ca.gov",
      "phoneNumber": "9017951714",
      "dateJoined": "2021-07-10 19:12:47",
      "status": "blacklisted"
    }, {
      "id": "01J12AR7XFV8QC8YSHX0F5G2JH",
      "organization": "Bashirian Inc",
      "userName": "Raffaello Thirtle",
      "email": "rthirtle13@uol.com.br",
      "phoneNumber": "5968292358",
      "dateJoined": "2021-01-15 09:21:01",
      "status": "pending"
    }, {
      "id": "01J12AR7XG1AG85239644K0R4C",
      "organization": "Erdman, Koepp and Price",
      "userName": "Roslyn Truluck",
      "email": "rtruluck14@mapy.cz",
      "phoneNumber": "1873764939",
      "dateJoined": "2022-03-16 18:27:54",
      "status": "pending"
    }, {
      "id": "01J12AR7XHB486289ZB9X83629",
      "organization": "Schulist-Adams",
      "userName": "Ronny Celiz",
      "email": "rceliz15@51.la",
      "phoneNumber": "6812432084",
      "dateJoined": "2022-06-11 13:02:56",
      "status": "inactive"
    }, {
      "id": "01J12AR7XJGKQW0X6DADGRAPAD",
      "organization": "Dietrich LLC",
      "userName": "Maritsa Paver",
      "email": "mpaver16@newyorker.com",
      "phoneNumber": "5578682160",
      "dateJoined": "2024-04-01 20:04:12",
      "status": "pending"
    }, {
      "id": "01J12AR7XK0RCY3ZEC3QMGH73T",
      "organization": "Klocko, Hane and Steuber",
      "userName": "Jamil Janse",
      "email": "jjanse17@indiatimes.com",
      "phoneNumber": "7941277119",
      "dateJoined": "2022-08-24 03:59:22",
      "status": "inactive"
    }, {
      "id": "01J12AR7XMXCHY1067PEA2A6B5",
      "organization": "Reichel-Hauck",
      "userName": "Page Watters",
      "email": "pwatters18@umn.edu",
      "phoneNumber": "3431498954",
      "dateJoined": "2024-06-12 09:37:38",
      "status": "blacklisted"
    }, {
      "id": "01J12AR7XNZ4DB6K9K78Q3J4GQ",
      "organization": "Schultz Group",
      "userName": "Emelyne Abramson",
      "email": "eabramson19@ucsd.edu",
      "phoneNumber": "6807663708",
      "dateJoined": "2021-06-16 15:35:14",
      "status": "inactive"
    }, {
      "id": "01J12AR7XPNDMGZPHR2W1DC9WS",
      "organization": "Rosenbaum Inc",
      "userName": "Engelbert Casini",
      "email": "ecasini1a@nydailynews.com",
      "phoneNumber": "8782129765",
      "dateJoined": "2023-06-27 17:44:41",
      "status": "pending"
    }, {
      "id": "01J12AR7XQ59PSWK52TRKFD4PK",
      "organization": "Torp-Volkman",
      "userName": "Elita Whickman",
      "email": "ewhickman1b@wordpress.com",
      "phoneNumber": "8915180433",
      "dateJoined": "2022-10-30 14:19:52",
      "status": "active"
    }, {
      "id": "01J12AR7XRGNYQ21V5225BTQM0",
      "organization": "Funk-Hessel",
      "userName": "Rudy Blatcher",
      "email": "rblatcher1c@columbia.edu",
      "phoneNumber": "2849569911",
      "dateJoined": "2023-03-04 10:32:15",
      "status": "inactive"
    }, {
      "id": "01J12AR7XSD6PPN8NPMG3MTAZQ",
      "organization": "Upton LLC",
      "userName": "Rozamond Klimkov",
      "email": "rklimkov1d@yandex.ru",
      "phoneNumber": "9729965112",
      "dateJoined": "2023-11-27 04:57:38",
      "status": "inactive"
    }, {
      "id": "01J12AR7XTQS9Q3Q0BH85YP8H5",
      "organization": "Gusikowski LLC",
      "userName": "Korry Borer",
      "email": "kborer1e@google.co.uk",
      "phoneNumber": "6065164299",
      "dateJoined": "2023-05-23 18:07:19",
      "status": "inactive"
    }, {
      "id": "01J12AR7XVYAREFRY2SZ5M6ASP",
      "organization": "Mayer, Luettgen and Bartoletti",
      "userName": "Gabe Duplain",
      "email": "gduplain1f@bloglines.com",
      "phoneNumber": "1273380515",
      "dateJoined": "2021-01-03 20:19:07",
      "status": "pending"
    }, {
      "id": "01J12AR7XWC8BQC3HNRFP1HDQM",
      "organization": "Toy LLC",
      "userName": "Morly Leynagh",
      "email": "mleynagh1g@hhs.gov",
      "phoneNumber": "6911405361",
      "dateJoined": "2020-12-07 17:28:48",
      "status": "active"
    }, {
      "id": "01J12AR7XX99QTJCV289TN53T4",
      "organization": "Fisher, Mueller and Stroman",
      "userName": "Cleon Ramplee",
      "email": "cramplee1h@hostgator.com",
      "phoneNumber": "4741374420",
      "dateJoined": "2020-06-24 01:14:05",
      "status": "pending"
    }, {
      "id": "01J12AR7XYD7RTGS9D6EK723EF",
      "organization": "Kuhlman-Mueller",
      "userName": "Tristam Brunroth",
      "email": "tbrunroth1i@wikimedia.org",
      "phoneNumber": "7613414992",
      "dateJoined": "2021-10-14 13:33:38",
      "status": "blacklisted"
    }, {
      "id": "01J12AR7XZR86VKSMYV378C0B1",
      "organization": "Reichert-Jones",
      "userName": "Humphrey Whitsun",
      "email": "hwhitsun1j@about.com",
      "phoneNumber": "5443092017",
      "dateJoined": "2024-03-20 09:24:45",
      "status": "inactive"
    }, {
      "id": "01J12AR7Y0RPHGDQSJ5X6BT1XB",
      "organization": "Blanda-Hettinger",
      "userName": "Bessie Shrieves",
      "email": "bshrieves1k@sfgate.com",
      "phoneNumber": "8144229793",
      "dateJoined": "2022-02-01 03:50:27",
      "status": "pending"
    }, {
      "id": "01J12AR7Y17QG6VG73HDSZYF8K",
      "organization": "Ward, Purdy and Skiles",
      "userName": "Maia Frantzen",
      "email": "mfrantzen1l@noaa.gov",
      "phoneNumber": "6586744467",
      "dateJoined": "2023-04-18 13:50:15",
      "status": "blacklisted"
    }, {
      "id": "01J12AR7Y24AT6T2Y8E14RQE4T",
      "organization": "Schultz Inc",
      "userName": "Bourke Speechly",
      "email": "bspeechly1m@sitemeter.com",
      "phoneNumber": "7723557306",
      "dateJoined": "2022-11-28 06:43:19",
      "status": "inactive"
    }, {
      "id": "01J12AR7Y33E2030JCJMHQXB20",
      "organization": "Conn-Okuneva",
      "userName": "Danila Day",
      "email": "dday1n@webeden.co.uk",
      "phoneNumber": "3186822348",
      "dateJoined": "2021-03-23 01:49:13",
      "status": "blacklisted"
    }, {
      "id": "01J12AR7Y3W02PGGWDSNWN1BGV",
      "organization": "Mills-Paucek",
      "userName": "Stanly Broddle",
      "email": "sbroddle1o@google.ru",
      "phoneNumber": "4547680941",
      "dateJoined": "2023-09-11 18:08:16",
      "status": "blacklisted"
    }, {
      "id": "01J12AR7Y4W3CTKB8M304QKE98",
      "organization": "McLaughlin-Schiller",
      "userName": "Will Brackstone",
      "email": "wbrackstone1p@howstuffworks.com",
      "phoneNumber": "5374462584",
      "dateJoined": "2021-05-16 06:47:49",
      "status": "inactive"
    }, {
      "id": "01J12AR7Y6MD7GR5BS1AMFD2YA",
      "organization": "Beatty-Lynch",
      "userName": "Ephrem Rutigliano",
      "email": "erutigliano1q@msu.edu",
      "phoneNumber": "9792081312",
      "dateJoined": "2024-06-14 22:53:38",
      "status": "inactive"
    }, {
      "id": "01J12AR7Y6452H0A5QEN4N5XY9",
      "organization": "Bailey LLC",
      "userName": "Theodosia Schulz",
      "email": "tschulz1r@comsenz.com",
      "phoneNumber": "1898896850",
      "dateJoined": "2022-05-31 00:13:14",
      "status": "active"
    }, {
      "id": "01J12AR7Y75P0KZXJ5Z7CH6QMV",
      "organization": "Bernier, Bashirian and Mueller",
      "userName": "Karia Hryncewicz",
      "email": "khryncewicz1s@cyberchimps.com",
      "phoneNumber": "6477764335",
      "dateJoined": "2022-08-10 03:43:53",
      "status": "pending"
    }, {
      "id": "01J12AR7Y8JBVMCTHC3BBVJCGW",
      "organization": "Koss LLC",
      "userName": "Sophronia Wohler",
      "email": "swohler1t@about.com",
      "phoneNumber": "5601273123",
      "dateJoined": "2022-12-10 04:24:51",
      "status": "blacklisted"
    }, {
      "id": "01J12AR7Y9J9A69B3PKBH12RZ0",
      "organization": "Volkman, Olson and Batz",
      "userName": "Janis Nares",
      "email": "jnares1u@chronoengine.com",
      "phoneNumber": "5447078688",
      "dateJoined": "2021-06-29 02:47:52",
      "status": "inactive"
    }, {
      "id": "01J12AR7YB69G3ZCWQBG1J45RY",
      "organization": "Torp Group",
      "userName": "June Mathissen",
      "email": "jmathissen1v@purevolume.com",
      "phoneNumber": "8259098209",
      "dateJoined": "2021-10-04 10:29:44",
      "status": "pending"
    }, {
      "id": "01J12AR7YC3P3VZVP680EWRHE7",
      "organization": "Lueilwitz-Lang",
      "userName": "Berny Nowick",
      "email": "bnowick1w@deviantart.com",
      "phoneNumber": "4221672402",
      "dateJoined": "2024-05-20 19:43:47",
      "status": "blacklisted"
    }, {
      "id": "01J12AR7YDMXY4616V03TQWVDN",
      "organization": "Moore, Gislason and Abernathy",
      "userName": "Tad Rudolf",
      "email": "trudolf1x@dmoz.org",
      "phoneNumber": "4691513142",
      "dateJoined": "2022-12-18 16:54:46",
      "status": "blacklisted"
    }, {
      "id": "01J12AR7YEZ1YJW72K5DRTG2X8",
      "organization": "Emard-Kuhn",
      "userName": "Parke Dunabie",
      "email": "pdunabie1y@intel.com",
      "phoneNumber": "9906506277",
      "dateJoined": "2021-05-04 22:45:03",
      "status": "inactive"
    }, {
      "id": "01J12AR7YFBSAPJNWNJK1Q4CGX",
      "organization": "Bayer, Walter and Metz",
      "userName": "Alic Matusiak",
      "email": "amatusiak1z@delicious.com",
      "phoneNumber": "1311949057",
      "dateJoined": "2021-09-13 09:07:57",
      "status": "blacklisted"
    }, {
      "id": "01J12AR7YGATD6BSASRXZSTVQ2",
      "organization": "Nolan and Sons",
      "userName": "Darius Goudard",
      "email": "dgoudard20@globo.com",
      "phoneNumber": "7541671678",
      "dateJoined": "2021-09-09 17:26:50",
      "status": "active"
    }, {
      "id": "01J12AR7YH8SP6FQQ06240Z0R1",
      "organization": "Considine-Wyman",
      "userName": "Serge Fogel",
      "email": "sfogel21@yellowpages.com",
      "phoneNumber": "2038260281",
      "dateJoined": "2022-08-12 09:55:42",
      "status": "active"
    }, {
      "id": "01J12AR7YJERE8N1QMG280BAW0",
      "organization": "Beahan-Dach",
      "userName": "Lyle Sellers",
      "email": "lsellers22@time.com",
      "phoneNumber": "8447922481",
      "dateJoined": "2020-12-19 05:30:11",
      "status": "pending"
    }, {
      "id": "01J12AR7YJHSY7VSXAJNSCBYG0",
      "organization": "Donnelly-Buckridge",
      "userName": "Giffie Gaiter",
      "email": "ggaiter23@patch.com",
      "phoneNumber": "6275962904",
      "dateJoined": "2021-01-07 20:50:52",
      "status": "pending"
    }, {
      "id": "01J12AR7YK0C5BNCANWQ6S53DC",
      "organization": "Metz-O'Connell",
      "userName": "Lilla Coppins",
      "email": "lcoppins24@barnesandnoble.com",
      "phoneNumber": "9351546693",
      "dateJoined": "2020-12-25 01:02:44",
      "status": "blacklisted"
    }, {
      "id": "01J12AR7YMQF2F5TPY2SV5SJYS",
      "organization": "Okuneva, Leuschke and Blick",
      "userName": "Gwendolen Tarrier",
      "email": "gtarrier25@trellian.com",
      "phoneNumber": "3345321672",
      "dateJoined": "2022-11-09 22:54:08",
      "status": "active"
    }, {
      "id": "01J12AR7YP6NN3ECKHWDKXKYZP",
      "organization": "Barton Inc",
      "userName": "Brunhilda Conring",
      "email": "bconring26@state.tx.us",
      "phoneNumber": "1726534412",
      "dateJoined": "2023-04-05 04:38:45",
      "status": "blacklisted"
    }, {
      "id": "01J12AR7YQTK6R56VD2JVYN6Y6",
      "organization": "Hodkiewicz Group",
      "userName": "Dion Rollinson",
      "email": "drollinson27@wikipedia.org",
      "phoneNumber": "5763519446",
      "dateJoined": "2023-04-26 04:13:40",
      "status": "active"
    }, {
      "id": "01J12AR7YRGSYGDF3AMTRRBSPV",
      "organization": "McGlynn, McGlynn and Dickens",
      "userName": "Egon Lissett",
      "email": "elissett28@ed.gov",
      "phoneNumber": "4104436403",
      "dateJoined": "2023-07-11 22:06:51",
      "status": "active"
    }, {
      "id": "01J12AR7YR96Z2W8PJFCEDWTTR",
      "organization": "Shields and Sons",
      "userName": "Adey Linder",
      "email": "alinder29@booking.com",
      "phoneNumber": "6061552712",
      "dateJoined": "2023-09-07 02:05:40",
      "status": "blacklisted"
    }, {
      "id": "01J12AR7YSF6RHW4N17JQKGZWB",
      "organization": "McDermott, Kunde and Greenfelder",
      "userName": "Ravid Shepley",
      "email": "rshepley2a@godaddy.com",
      "phoneNumber": "5502921503",
      "dateJoined": "2023-11-08 13:09:30",
      "status": "active"
    }, {
      "id": "01J12AR7YTGMSDHGXJDH5EXHP5",
      "organization": "Batz, Sporer and Grimes",
      "userName": "Stormi Peltz",
      "email": "speltz2b@sourceforge.net",
      "phoneNumber": "5449698119",
      "dateJoined": "2023-10-26 02:19:42",
      "status": "pending"
    }, {
      "id": "01J12AR7YV2EBBWY9NZNYNQRGK",
      "organization": "Hodkiewicz, Walsh and Abshire",
      "userName": "Alecia Willshee",
      "email": "awillshee2c@unc.edu",
      "phoneNumber": "1408561309",
      "dateJoined": "2022-01-10 17:34:01",
      "status": "blacklisted"
    }, {
      "id": "01J12AR7YW9AZB350DQX563N5C",
      "organization": "Gutmann-Reichert",
      "userName": "Angela Deesly",
      "email": "adeesly2d@g.co",
      "phoneNumber": "9914588661",
      "dateJoined": "2021-12-01 10:38:42",
      "status": "inactive"
    }, {
      "id": "01J12AR7YXS2NCDJ132369AHCP",
      "organization": "Brakus-Hagenes",
      "userName": "Jesselyn Bullock",
      "email": "jbullock2e@google.com",
      "phoneNumber": "8857836859",
      "dateJoined": "2023-01-01 17:54:37",
      "status": "pending"
    }, {
      "id": "01J12AR7YYXBXF606709C4NKK2",
      "organization": "Wyman, Hintz and Cummerata",
      "userName": "Ddene Margrie",
      "email": "dmargrie2f@senate.gov",
      "phoneNumber": "1393425141",
      "dateJoined": "2022-06-05 11:04:45",
      "status": "inactive"
    }, {
      "id": "01J12AR7YZB73WGV7CMZJFQQ5K",
      "organization": "Okuneva-Littel",
      "userName": "Winfield Piper",
      "email": "wpiper2g@ehow.com",
      "phoneNumber": "8911665558",
      "dateJoined": "2024-01-24 10:40:41",
      "status": "pending"
    }, {
      "id": "01J12AR7Z0APC14RDQXQP6CX75",
      "organization": "Weissnat, Kertzmann and Rippin",
      "userName": "Fanni Stanesby",
      "email": "fstanesby2h@whitehouse.gov",
      "phoneNumber": "5638714524",
      "dateJoined": "2023-12-24 13:37:08",
      "status": "blacklisted"
    }, {
      "id": "01J12AR7Z1TFRNQ08CNE1037J4",
      "organization": "Hickle, Schumm and Kassulke",
      "userName": "Paten Lorne",
      "email": "plorne2i@cbsnews.com",
      "phoneNumber": "5468305521",
      "dateJoined": "2024-04-29 09:13:21",
      "status": "active"
    }, {
      "id": "01J12AR7Z2B0HBFRESXXDDZPAR",
      "organization": "Streich-Greenholt",
      "userName": "Evered Greet",
      "email": "egreet2j@usda.gov",
      "phoneNumber": "3256841480",
      "dateJoined": "2023-02-23 21:01:50",
      "status": "pending"
    }, {
      "id": "01J12AR7Z3YQ0XMEYHD84PSR2D",
      "organization": "Ledner and Sons",
      "userName": "Garwin Duffell",
      "email": "gduffell2k@shutterfly.com",
      "phoneNumber": "2036866300",
      "dateJoined": "2022-04-13 05:03:03",
      "status": "blacklisted"
    }, {
      "id": "01J12AR7Z4NT6T6D3WQ28ABWJP",
      "organization": "Ruecker-Grimes",
      "userName": "Faith Forkan",
      "email": "fforkan2l@addthis.com",
      "phoneNumber": "2223642524",
      "dateJoined": "2023-03-29 23:27:02",
      "status": "inactive"
    }, {
      "id": "01J12AR7Z50N8KA9K3AWP5Y9CD",
      "organization": "Bechtelar-Jaskolski",
      "userName": "Rhoda Beades",
      "email": "rbeades2m@marriott.com",
      "phoneNumber": "7627496937",
      "dateJoined": "2023-03-12 05:50:57",
      "status": "inactive"
    }, {
      "id": "01J12AR7Z6PW2W7ETKHFZ4H2ND",
      "organization": "Gusikowski, Lynch and Wehner",
      "userName": "Adolph McKyrrelly",
      "email": "amckyrrelly2n@npr.org",
      "phoneNumber": "2092493987",
      "dateJoined": "2023-05-26 08:22:20",
      "status": "inactive"
    }, {
      "id": "01J12AR7Z76ANJDACRMCV709P8",
      "organization": "Mueller, Spencer and Windler",
      "userName": "Brietta Corssen",
      "email": "bcorssen2o@dedecms.com",
      "phoneNumber": "1349868196",
      "dateJoined": "2021-04-21 23:59:42",
      "status": "blacklisted"
    }, {
      "id": "01J12AR7Z8F0GCQE998YSY1SR7",
      "organization": "Bartoletti, Kutch and Schamberger",
      "userName": "Renata Dayborne",
      "email": "rdayborne2p@tinyurl.com",
      "phoneNumber": "1059569990",
      "dateJoined": "2022-11-22 16:28:47",
      "status": "pending"
    }, {
      "id": "01J12AR7ZADTR73T7FR8RAJZ4R",
      "organization": "Lindgren-Rath",
      "userName": "Timotheus Andreolli",
      "email": "tandreolli2q@bloomberg.com",
      "phoneNumber": "9061640655",
      "dateJoined": "2023-11-15 06:41:39",
      "status": "inactive"
    }, {
      "id": "01J12AR7ZBTG4Y4QCKEJM80FKQ",
      "organization": "Ziemann, Miller and Schowalter",
      "userName": "Dreddy Gower",
      "email": "dgower2r@w3.org",
      "phoneNumber": "6561966162",
      "dateJoined": "2020-09-13 16:23:36",
      "status": "blacklisted"
    }
  ],
  "userDetails": {
    "id": "01J13YY1ESR3H7MYV93Q79K8SA",
    "userPhoto": "/images/userIcon.png",
    "userTier": 1,
    "personalInfo": {
      "userName": "Grace Effiom",
      "userRegNo": "LSQFf587g90",
      "phoneNumber": "07060780922",
      "email": "grace@gmail.com",
      "bvn": "07060780922",
      "gender": "female",
      "maritalStatus": "single",
      "children": "none",
      "typeOfResidence": "Parent's Apartment"
    },
    "educationAndEmployment": {
      "educationLevel": "B.Sc",
      "employmentStatus": "employed",
      "employmentSector": "FinTech",
      "employmentDuration": "2 years",
      "officeEmail": "grace@lendsqr.com",
      "monthlyIncomeRange": {
        "lowRange": 200000,
        "highRange": 400000
      },
      "loanRepayment": 40000
    },
    "socials": {
      "twitter": "@grace_effiom",
      "facebook": "Grace Effiom",
      "instagram": "@grace_effiom"
    },
    "guarantors": [
      {
        "id": 1,
        "guarantorName": "Debby Ogana",
        "guarantorPhoneNumber": "07060780922",
        "email": "debby@gmail.com",
        "relationship": "Sister"
      },
      {
        "id": 2,
        "guarantorName": "Debby Ogana",
        "guarantorPhoneNumber": "07060780922",
        "email": "debby@gmail.com",
        "relationship": "Sister"
      }
    ],
    "bankDetails": {
      "id": 1,
      "bankName": "Providus Bank",
      "accountNumber": "9912345678",
      "balance": 200000
    }
  }
}